phonetic_alphabet/__init__.py
phonetic_alphabet/helpers.py
phonetic_alphabet/main.py
phonetic_alphabet/data/__init__.py
phonetic_alphabet/data/icao_alphabet.py
phonetic_alphabet/data/numbers.py
tests/__init__.py
tests/test_helpers.py
tests/test_phonetic_alphabet.py
phonetic_alphabet-0.1.0.dist-info/LICENSE.md
phonetic_alphabet-0.1.0.dist-info/METADATA
phonetic_alphabet-0.1.0.dist-info/WHEEL
phonetic_alphabet-0.1.0.dist-info/top_level.txt
phonetic_alphabet-0.1.0.dist-info/RECORD
