Metadata-Version: 2.1
Name: phonetic_alphabet
Version: 0.1.0
Summary: Convert characters and digits to phonetic alphabet equivalents.
Home-page: http://github.com/ryderdamen/phonetic-alphabet
Author: Ryder Damen
Author-email: dev@ryderdamen.com
License: MIT
Keywords: phonetic alphabet aviation flight alpha bravo charlie niner
Platform: UNKNOWN
